east/__init__.py
east/langs/__init__.py
east/langs/json.py
python_east-0.0.4.dist-info/METADATA
python_east-0.0.4.dist-info/WHEEL
python_east-0.0.4.dist-info/top_level.txt
python_east-0.0.4.dist-info/RECORD
